skidward/__init__.py
skidward/__main__.py
skidward/app.py
skidward/backend.py
skidward/models.py
skidward/task_runner.py
skidward/scheduler/__init__.py
skidward/scheduler/scheduler.py
skidward/web/README.md
skidward/web/__init__.py
skidward/web/forms.py
skidward/web/views.py
skidward/web/templates/_confirm.html
skidward/web/templates/index.html
skidward/web/templates/macro_render_field.html
skidward/web/templates/admin/index.html
skidward/web/templates/log/logview.html
skidward/web/templates/security/_macros.html
skidward/web/templates/security/login_user.html
skidward/web/templates/task/configure.html
skidward/worker_detector/__init__.py
skidward/worker_detector/namespace_module_manager.py
skidward-0.0.1.dev434.dist-info/AUTHORS
skidward-0.0.1.dev434.dist-info/LICENSE
skidward-0.0.1.dev434.dist-info/METADATA
skidward-0.0.1.dev434.dist-info/WHEEL
skidward-0.0.1.dev434.dist-info/pbr.json
skidward-0.0.1.dev434.dist-info/top_level.txt
skidward-0.0.1.dev434.dist-info/RECORD
