Metadata-Version: 2.1
Name: skidward
Version: 0.0.1.dev434
Summary: scheduler for python scripts
Home-page: https://gitlab.adimian.com/open-source/skidward/
Author: See AUTHORS
Author-email: contact@adimian.com
License: UNKNOWN
Platform: UNKNOWN
Classifier: Development Status :: 4 - Beta
Classifier: Operating System :: POSIX
Classifier: License :: OSI Approved :: MIT License
Classifier: Programming Language :: Python
Classifier: Programming Language :: Python :: 3.6
Classifier: Programming Language :: Python :: 3.7
Requires-Dist: bcrypt (==3.1.6)
Requires-Dist: cronex (==0.1.3.1)
Requires-Dist: Flask (==1.0.2)
Requires-Dist: Flask-Admin (==1.5.3)
Requires-Dist: Flask-Security (==3.0.0)
Requires-Dist: Flask-SQLAlchemy (==2.3.2)
Requires-Dist: Flask-Migrate (==2.4.0)
Requires-Dist: redis (==3.0.1)
Requires-Dist: SQLAlchemy (==1.2.16)
Requires-Dist: redis-log-handler (==0.0.1.dev32)
Requires-Dist: psycopg2-binary (==2.7.6.1)
Requires-Dist: python-dotenv (==0.10.1)
Requires-Dist: PyYAML (==3.13)
Requires-Dist: SQLAlchemy-Utils (==0.33.11)
Requires-Dist: fire (==0.1.3)
